Metadata-Version: 2.1
Name: tbodyparser
Version: 1.0.4
Summary: web table body parser based on pyquery
Home-page: https://github.com/MrBigBlake/tbodyparser
Author: MrBigB
Author-email: lowbeeland@163.com
License: UNKNOWN
Platform: UNKNOWN
Classifier: Programming Language :: Python :: 3
Classifier: License :: OSI Approved :: MIT License
Classifier: Operating System :: OS Independent
Requires-Python: >=3.6
